pybrick/__init__.py
pybrick/ptest.csv
pybrick/pybrick.py
pybrick-0.2.99.dist-info/METADATA
pybrick-0.2.99.dist-info/WHEEL
pybrick-0.2.99.dist-info/top_level.txt
pybrick-0.2.99.dist-info/RECORD
