Metadata-Version: 2.1
Name: pybrick
Version: 0.2.99
Summary: UNKNOWN
Home-page: UNKNOWN
License: UNKNOWN
Platform: UNKNOWN
Requires-Dist: pandas
Requires-Dist: psycopg2
Requires-Dist: sqlalchemy
